<XnaContent>
  <Asset Type="MyDataTypes.LevelObjectData[]">
    <Item>
      <ObjectType>Background</ObjectType>
      <ObjectName>Room9</ObjectName>
      <Location>807 1109</Location>
    </Item>

    <!--HUD-->
    <Item>
      <ObjectType>HUD</ObjectType>
      <ObjectName>HUDBackground</ObjectName>
      <Location>16 -168</Location>
    </Item>
    <Item>
      <ObjectType>HUD</ObjectType>
      <ObjectName>HUDLevel</ObjectName>
      <Location>64 -144</Location>
    </Item>
    <Item>
      <ObjectType>HUD</ObjectType>
      <ObjectName>HUDLevelNumber</ObjectName>
      <Location>208 -144</Location>
    </Item>
    <Item>
      <ObjectType>HUD</ObjectType>
      <ObjectName>HUDLevelBlankBackground</ObjectName>
      <Location>63 -120</Location>
    </Item>
    <Item>
      <ObjectType>HUD</ObjectType>
      <ObjectName>HUDMap</ObjectName>
      <Location>112 -96</Location>
    </Item>
    <Item>
      <ObjectType>HUD</ObjectType>
      <ObjectName>HUDMapLocation</ObjectName>
      <Location>118 -72</Location>
    </Item>
    <Item>
      <ObjectType>HUD</ObjectType>
      <ObjectName>HUDCompassLocation</ObjectName>
      <Location>214 -84</Location>
    </Item>
    <Item>
      <ObjectType>HUD</ObjectType>
      <ObjectName>HUDXSymbol</ObjectName>
      <Location>304 -120</Location>
    </Item>
    <Item>
      <ObjectType>HUD</ObjectType>
      <ObjectName>HUDGemNumbers</ObjectName>
      <Location>328 -120</Location>
    </Item>
    <Item>
      <ObjectType>HUD</ObjectType>
      <ObjectName>HUDXSymbol</ObjectName>
      <Location>304 -72</Location>
    </Item>
    <Item>
      <ObjectType>HUD</ObjectType>
      <ObjectName>HUDKeyNumbers</ObjectName>
      <Location>328 -72</Location>
    </Item>
    <Item>
      <ObjectType>HUD</ObjectType>
      <ObjectName>HUDXSymbol</ObjectName>
      <Location>304 -48</Location>
    </Item>
    <Item>
      <ObjectType>HUD</ObjectType>
      <ObjectName>HUDBombNumbers</ObjectName>
      <Location>328 -48</Location>
    </Item>
    <Item>
      <ObjectType>HUD</ObjectType>
      <ObjectName>HUDLifeBlankBackground</ObjectName>
      <Location>544 -72</Location>
    </Item>
    <Item>
      <ObjectType>HUD</ObjectType>
      <ObjectName>HUDHealth</ObjectName>
      <Location>544 -48</Location>
    </Item>
    <Item>
      <ObjectType>HUD</ObjectType>
      <ObjectName>HUDWoodSword</ObjectName>
      <Location>472 -96</Location>
    </Item>
    <Item>
      <ObjectType>HUD</ObjectType>
      <ObjectName>HUDArrow</ObjectName>
      <Location>400 -96</Location>
    </Item>


    <Item>
      <ObjectType>Link</ObjectType>
      <ObjectName>Link</ObjectName>
      <Location>200 200</Location>
    </Item>

    <!--Walls-->
    <Item>
      <ObjectType>Block</ObjectType>
      <ObjectName>HorizontalWall</ObjectName>
      <Location>0 0</Location>
    </Item>
    <Item>
      <ObjectType>Block</ObjectType>
      <ObjectName>HorizontalWall</ObjectName>
      <Location>0 450</Location>
    </Item>
    <Item>
      <ObjectType>Block</ObjectType>
      <ObjectName>VerticalWall</ObjectName>
      <Location>0 0</Location>
    </Item>
    <Item>
      <ObjectType>Block</ObjectType>
      <ObjectName>VerticalWall</ObjectName>
      <Location>700 0</Location>
    </Item>

    <!--Blocks-->
    <Item>
      <ObjectType>Block</ObjectType>
      <ObjectName>Block</ObjectName>
      <Location>350 250</Location>
    </Item>

    <!--Doors-->
    <Item>
      <ObjectType>Block</ObjectType>
      <ObjectName>Door</ObjectName>
      <Location>375 449</Location>
      <DestinationRoomNumber>5</DestinationRoomNumber>
      <Direction>Down</Direction>
      <Locked>False</Locked>
    </Item>
    <Item>
      <ObjectType>Block</ObjectType>
      <ObjectName>Door</ObjectName>
      <Location>51 250</Location>
      <DestinationRoomNumber>8</DestinationRoomNumber>
      <Direction>Left</Direction>
      <Locked>True</Locked>
    </Item>
    <Item>
      <ObjectType>Block</ObjectType>
      <ObjectName>Door</ObjectName>
      <Location>699 250</Location>
      <DestinationRoomNumber>10</DestinationRoomNumber>
      <Direction>Right</Direction>
      <Locked>False</Locked>
    </Item>

    <!--Collectables-->

    <!--Enemies-->
    <Item>
      <ObjectType>Enemy</ObjectType>
      <ObjectName>Gel</ObjectName>
      <Location>350 150</Location>
    </Item>
    <Item>
      <ObjectType>Enemy</ObjectType>
      <ObjectName>Gel</ObjectName>
      <Location>400 350</Location>
    </Item>
    <Item>
      <ObjectType>Enemy</ObjectType>
      <ObjectName>Gel</ObjectName>
      <Location>450 150</Location>
    </Item>

    <!--Enemy Spawners-->
    <Item>
      <ObjectType>GelSpawner</ObjectType>
      <ObjectName>GelSpawner</ObjectName>
      <Location>101 101</Location>
    </Item>
  </Asset>
</XnaContent>